sensor_simulation/__init__.py
sensor_simulation/mqtt_client.py
sensor_simulation/sensor_manager.py
sensor_simulation/clients/__init__.py
sensor_simulation/clients/aws_mqtt_client.py
sensor_simulation/clients/azure_mqtt_client.py
sensor_simulation/clients/azure_token_generator.py
sensor_simulation/clients/mqtt_client.py
sensor_simulation/config/__init__.py
sensor_simulation/config/logger.py
sensor_simulation/config/parsers/__init__.py
sensor_simulation/config/parsers/toml_parser.py
sensor_simulation/sensors/__init__.py
sensor_simulation/sensors/base_sensor.py
sensor_simulation/sensors/humidity_sensor.py
sensor_simulation/sensors/light_intensity_sensor.py
sensor_simulation/sensors/ph_sensor.py
sensor_simulation/sensors/temperature_sensor.py
sensor_simulation/sensors/water_level_sensor.py
tests/__init__.py
tests/test_sensor_manager.py
tests/config/__init__.py
tests/config/test_parser.py
tests/sensors/__init__.py
tests/sensors/test_humidity_sensor.py
tests/sensors/test_light_intensity_sensor.py
tests/sensors/test_ph_sensor.py
tests/sensors/test_temperature_sensor.py
tests/sensors/test_water_level_sensor.py
pysor-0.1.2.dist-info/LICENSE
pysor-0.1.2.dist-info/METADATA
pysor-0.1.2.dist-info/WHEEL
pysor-0.1.2.dist-info/top_level.txt
pysor-0.1.2.dist-info/RECORD
