Metadata-Version: 2.1
Name: pysor
Version: 0.1.2
Summary: A Python package for sensor simulations
Home-page: https://github.com/CodeSwallow/pysor
Author: Isai Ramirez
Author-email: isai.ramirez.stamaria15@gmail.com
License: MIT
Keywords: mqtt sensor simulation
Classifier: Development Status :: 3 - Alpha
Classifier: Intended Audience :: Developers
Classifier: License :: OSI Approved :: MIT License
Classifier: Programming Language :: Python :: 3
Classifier: Programming Language :: Python :: 3.9
Classifier: Programming Language :: Python :: 3.10
Classifier: Programming Language :: Python :: 3.11
Requires-Python: >=3.9, <4
License-File: LICENSE
Requires-Dist: paho-mqtt
Requires-Dist: toml (==0.10.2) ; python_version<"3.11"
